fsvm/__init__.py
fsvm/_fuzzy_svc.py
fsvm/_version.py
fsvm/tests/__init__.py
fsvm/tests/test_common.py
fsvm/tests/test_fuzzy_svc.py
fsvm/utils/__init__.py
fsvm/utils/discovery.py
fsvm/utils/tests/__init__.py
fsvm/utils/tests/test_discovery.py
fsvm-0.1.0.dist-info/LICENSE
fsvm-0.1.0.dist-info/METADATA
fsvm-0.1.0.dist-info/WHEEL
fsvm-0.1.0.dist-info/top_level.txt
fsvm-0.1.0.dist-info/RECORD
