Metadata-Version: 2.1
Name: fsvm
Version: 0.1.0
Summary: A scikit-learn compatible Fuzzy Support Vector Machine implementation.
Author: Jakub Baliński
Project-URL: Homepage, https://github.com/balins/fsvm
Project-URL: Documentation, https://balins.github.io/fsvm
Project-URL: Issues, https://github.com/balins/fsvm/issues
Classifier: Programming Language :: Python :: 3
Classifier: Programming Language :: Python :: 3.9
Classifier: Programming Language :: Python :: 3.10
Classifier: Programming Language :: Python :: 3.11
Classifier: Programming Language :: Python :: 3.12
Classifier: License :: OSI Approved :: BSD License
Classifier: Operating System :: POSIX
Classifier: Operating System :: Unix
Classifier: Operating System :: MacOS
Classifier: Operating System :: Microsoft :: Windows
Requires-Python: >=3.9
License-File: LICENSE
Requires-Dist: scikit-learn >=1.4.2
Requires-Dist: numpy >=2.1
